README.md
setup.py
relext/README.md
relext/__init__.py
relext/doccano.md
relext/doccano.py
relext/evaluate.py
relext/finetune.py
relext/graph.py
relext/information_extraction.py
relext/keywords_textrank.py
relext/relation_extraction.py
relext/sentence_parser.py
relext/show_graph.py
relext/uie_model.py
relext/uie_predictor.py
relext/utils.py
relext/version.py
relext.egg-info/PKG-INFO
relext.egg-info/SOURCES.txt
relext.egg-info/dependency_links.txt
relext.egg-info/requires.txt
relext.egg-info/top_level.txt
relext/uie/__init__.py
relext/uie/process_data.py
relext/uie/run_seq2struct.py
relext/uie/evaluation/__init__.py
relext/uie/evaluation/constants.py
relext/uie/evaluation/scorer.py
relext/uie/evaluation/sel2record.py
relext/uie/seq2struct/__init__.py
relext/uie/seq2struct/data_collator.py
relext/uie/seq2struct/t5_bert_tokenizer.py
relext/uie/seq2struct/utils.py