Metadata-Version: 2.1
Name: relext
Version: 0.0.4
Summary: RelExt: A Tool for Relation Extraction from Text.
Home-page: https://github.com/shibing624/relext
Author: XuMing
Author-email: xuming624@qq.com
License: Apache 2.0
Keywords: relation extraction,relext,relation,extraction
Platform: UNKNOWN
Classifier: Intended Audience :: Developers
Classifier: Operating System :: OS Independent
Classifier: Natural Language :: Chinese (Simplified)
Classifier: Natural Language :: Chinese (Traditional)
Classifier: Programming Language :: Python
Classifier: Programming Language :: Python :: 3
Classifier: Topic :: Text Processing
Classifier: Topic :: Text Processing :: Indexing
Classifier: Topic :: Text Processing :: Linguistic
